{
  "cards": [
    {
      "id": "4f3e",
      "name": "Mário ",
      "text": "ESPANCA VOCÊ E SUA MULHER",
      "rotaImg": "https://i.pinimg.com/736x/97/25/72/972572f414b2f4fffe5515179c5c3509.jpg"
    },
    {
      "id": "10a9",
      "name": "ITS OVER",
      "text": "NUNCA SOBRA NADA para o betinha",
      "rotaImg": "https://i.pinimg.com/736x/35/90/b2/3590b2071bcbe188ff618dbd9d96ac37.jpg"
    },
    {
      "id": "996a",
      "name": "nisgar",
      "text": "aquele que te come por igual atrás do armário",
      "rotaImg": "https://i.pinimg.com/736x/55/aa/8f/55aa8faa5c4d2e8e14bc6f8ecbfcafa3.jpg"
    }
  ]
}